hint_calls.py
williballenthin_hint_calls_ida_plugin-0.1.2.dist-info/METADATA
williballenthin_hint_calls_ida_plugin-0.1.2.dist-info/WHEEL
williballenthin_hint_calls_ida_plugin-0.1.2.dist-info/entry_points.txt
williballenthin_hint_calls_ida_plugin-0.1.2.dist-info/top_level.txt
williballenthin_hint_calls_ida_plugin-0.1.2.dist-info/RECORD
